banner.py
perfect_banner-1.0.0.post1.dist-info/METADATA
perfect_banner-1.0.0.post1.dist-info/WHEEL
perfect_banner-1.0.0.post1.dist-info/top_level.txt
perfect_banner-1.0.0.post1.dist-info/RECORD
