Metadata-Version: 2.1
Name: perfect-banner
Version: 1.0.0.post1
Summary: Let text fit the screen
Author: phoenixR
Keywords: ascii art,art,text,string,terminal
